etpgrf/__init__.py
etpgrf/codec.py
etpgrf/comutil.py
etpgrf/config.py
etpgrf/defaults.py
etpgrf/hanging.py
etpgrf/hyphenation.py
etpgrf/layout.py
etpgrf/logger.py
etpgrf/quotes.py
etpgrf/sanitizer.py
etpgrf/symbols.py
etpgrf/typograph.py
etpgrf/unbreakables.py
etpgrf-0.1.3.dist-info/METADATA
etpgrf-0.1.3.dist-info/WHEEL
etpgrf-0.1.3.dist-info/top_level.txt
etpgrf-0.1.3.dist-info/RECORD
