Metadata-Version: 2.4
Name: etpgrf
Version: 0.1.3
Summary: Electro-Typographer: Python library for advanced web typography (non-breaking spaces, hyphenation, hanging punctuation and .
Author-email: Sergei Erjemin <erjemin@gmail.com>
License: MIT
Project-URL: Homepage, https://github.com/erjemin/etpgrf
Project-URL: Bug Tracker, https://github.com/erjemin/etpgrf/issues
Project-URL: Mirror (GitVerse), https://gitverse.ru/erjemin/etpgrf
Project-URL: Selfhosted (Gitea), https://gitverse.ru/erjemin/etpgrf
Keywords: typography,html,non-breaking-spaces,hanging-punctuation,hyphenation,russian,english
Classifier: Development Status :: 4 - Beta
Classifier: Intended Audience :: Developers
Classifier: Topic :: Text Processing :: Markup :: HTML
Classifier: Programming Language :: Python :: 3
Classifier: Programming Language :: Python :: 3.10
Classifier: Programming Language :: Python :: 3.11
Classifier: Programming Language :: Python :: 3.12
Classifier: License :: OSI Approved :: MIT License
Classifier: Operating System :: OS Independent
Requires-Python: >=3.10
Requires-Dist: beautifulsoup4>=4.10.0
Requires-Dist: lxml>=4.9.0
Requires-Dist: regex>=2022.1.18
